muspinsim/__init__.py
muspinsim/__main__.py
muspinsim/celio.py
muspinsim/constants.py
muspinsim/cpp.cp311-win_amd64.pyd
muspinsim/cython.cp311-win_amd64.pyd
muspinsim/experiment.py
muspinsim/fitting.py
muspinsim/hamiltonian.py
muspinsim/lindbladian.py
muspinsim/mpi.py
muspinsim/simconfig.py
muspinsim/spinop.py
muspinsim/spinsys.py
muspinsim/utils.py
muspinsim/validation.py
muspinsim/version.py
muspinsim/input/__init__.py
muspinsim/input/gipaw.py
muspinsim/input/input.py
muspinsim/input/keyword.py
muspinsim/input/larkeval.py
muspinsim/input/structure.py
muspinsim/input/variables.py
muspinsim/tests/__init__.py
muspinsim/tests/test_args.py
muspinsim/tests/test_celio.py
muspinsim/tests/test_config.py
muspinsim/tests/test_constants.py
muspinsim/tests/test_experiment.py
muspinsim/tests/test_fitting.py
muspinsim/tests/test_generator.py
muspinsim/tests/test_gipaw.py
muspinsim/tests/test_hamiltonian.py
muspinsim/tests/test_input.py
muspinsim/tests/test_lark.py
muspinsim/tests/test_lindbladian.py
muspinsim/tests/test_mpi.py
muspinsim/tests/test_spinop.py
muspinsim/tests/test_spinsys.py
muspinsim/tests/test_structure.py
muspinsim/tests/test_utils.py
muspinsim/tests/test_validation.py
muspinsim/tools/__init__.py
muspinsim/tools/generator.py
muspinsim-2.3.0.dist-info/LICENSE
muspinsim-2.3.0.dist-info/METADATA
muspinsim-2.3.0.dist-info/WHEEL
muspinsim-2.3.0.dist-info/entry_points.txt
muspinsim-2.3.0.dist-info/top_level.txt
muspinsim-2.3.0.dist-info/RECORD
