Metadata-Version: 2.1
Name: muspinsim
Version: 2.3.0
Summary: Full quantum simulation of muon experiments
Home-page: https://github.com/muon-spectroscopy-computational-project/muspinsim.git
Author: Simone Sturniolo
Author-email: simonesturniolo@gmail.com
Classifier: Programming Language :: Python :: 3
Classifier: License :: OSI Approved :: MIT License
Classifier: Operating System :: OS Independent
Classifier: Development Status :: 5 - Production/Stable
Classifier: Intended Audience :: Science/Research
Classifier: Topic :: Scientific/Engineering :: Chemistry
Classifier: Topic :: Scientific/Engineering :: Physics
Classifier: Topic :: Scientific/Engineering :: Information Analysis
Requires-Python: >=3.8
License-File: LICENSE
Requires-Dist: ase
Requires-Dist: numpy
Requires-Dist: scipy
Requires-Dist: soprano
Requires-Dist: lark
Requires-Dist: qutip
Requires-Dist: pybind11
Requires-Dist: Cython
Provides-Extra: dev
Requires-Dist: flake8 ; extra == 'dev'
Requires-Dist: black (>=22.3.0) ; extra == 'dev'
Requires-Dist: pytest ; extra == 'dev'
Requires-Dist: pre-commit ; extra == 'dev'
Provides-Extra: docs
Requires-Dist: mkdocs ; extra == 'docs'
Requires-Dist: pymdown-extensions ; extra == 'docs'
